dd_coresets/__init__.py
dd_coresets/ddc.py
dd_coresets/pipelines.py
dd_coresets-0.2.0.dist-info/licenses/LICENSE
dd_coresets-0.2.0.dist-info/METADATA
dd_coresets-0.2.0.dist-info/WHEEL
dd_coresets-0.2.0.dist-info/top_level.txt
dd_coresets-0.2.0.dist-info/RECORD
