Metadata-Version: 2.4
Name: dd-coresets
Version: 0.2.0
Summary: Density–Diversity Coresets (DDC) for dataset summarization and distributional approximation
Author-email: "Carlos R. B. Azevedo" <renatoaz@gmail.com>
License-Expression: MIT
Project-URL: Homepage, https://github.com/crbazevedo/dd-coresets
Project-URL: Repository, https://github.com/crbazevedo/dd-coresets
Project-URL: Issues, https://github.com/crbazevedo/dd-coresets/issues
Requires-Python: >=3.8
License-File: LICENSE
Requires-Dist: numpy>=1.24
Requires-Dist: scikit-learn>=1.2
Requires-Dist: matplotlib>=3.7
Requires-Dist: pandas>=2.0
Dynamic: license-file
